<?xml version="1.0" encoding="UTF-8"?>
<sponge xmlns="http://www.openksavi.org/sponge" xmlns:xsi="http://www.w3.org/2001/XMLSchema-instance"
    xsi:schemaLocation="http://www.openksavi.org/sponge http://www.openksavi.org/sponge/schema/config.xsd">

    <properties>
        <property name="sponge.home">.</property>
        <property name="groovy.classpath" system="true">${sponge.home}/examples/script/groovy/knowledge_base_script_overriding</property>
    </properties>

    <knowledgeBases>
        <knowledgeBase name="kb" type="groovy">
            <file>${sponge.home}/examples/script/groovy/knowledge_base_script_overriding.groovy</file>
        </knowledgeBase>
    </knowledgeBases>
</sponge>

